vsutils/__init__.py
vsutils/__main__.py
vsutils/ADMET/__init__.py
vsutils/ADMET/filters.py
vsutils/ADMET/mc_filter.py
vsutils-0.0.1.dist-info/METADATA
vsutils-0.0.1.dist-info/WHEEL
vsutils-0.0.1.dist-info/licenses/LICENSE
vsutils-0.0.1.dist-info/RECORD
