Metadata-Version: 2.3
Name: vsutils
Version: 0.0.1
Summary: Utility for reaction modeling using graph grammar
Project-URL: homepage, https://github.com/Vivi-tran/VSUtils
Project-URL: source, https://github.com/Vivi-tran/VSUtils
Project-URL: issues, https://github.com/Vivi-tran/VSUtils/issues
Author-email: Ngoc-Vi Nguyen TRAN <nguyen-ngoc-vi.tran.6279@student.uu.se>
Classifier: License :: OSI Approved :: MIT License
Classifier: Operating System :: OS Independent
Classifier: Programming Language :: Python :: 3
Requires-Python: >=3.11
Requires-Dist: joblib>=1.4.2
Requires-Dist: pandas>=2.2.2
Requires-Dist: rdkit>=2024.3.3
Requires-Dist: scopy>=1.2.5
